sqlite_anyio/__init__.py
sqlite_anyio/py.typed
sqlite_anyio/sqlite.py
sqlite_anyio-0.2.2.dist-info/METADATA
sqlite_anyio-0.2.2.dist-info/WHEEL
sqlite_anyio-0.2.2.dist-info/licenses/LICENSE
sqlite_anyio-0.2.2.dist-info/RECORD
