Metadata-Version: 2.3
Name: sqlite-anyio
Version: 0.2.2
Summary: Asynchronous client for SQLite using AnyIO
Project-URL: Source, https://github.com/davidbrochart/sqlite-anyio
Project-URL: Issues, https://github.com/davidbrochart/sqlite-anyio/issues
Author-email: Alex Grönholm <alex.gronholm@nextday.fi>, David Brochart <david.brochart@gmail.com>
License: This is the MIT license: http://www.opensource.org/licenses/mit-license.php
License-File: LICENSE
Classifier: Development Status :: 4 - Beta
Classifier: Intended Audience :: Developers
Classifier: License :: OSI Approved :: MIT License
Classifier: Programming Language :: Python
Classifier: Programming Language :: Python :: 3
Classifier: Programming Language :: Python :: 3.8
Classifier: Programming Language :: Python :: 3.9
Classifier: Programming Language :: Python :: 3.10
Classifier: Programming Language :: Python :: 3.11
Classifier: Programming Language :: Python :: 3.12
Classifier: Topic :: Database
Classifier: Typing :: Typed
Requires-Python: >=3.8
Requires-Dist: anyio<5.0,>=4.0
Provides-Extra: test
Requires-Dist: coverage[toml]<8,>=7; extra == 'test'
Requires-Dist: mypy; extra == 'test'
Requires-Dist: pytest<9,>=8; extra == 'test'
Requires-Dist: trio<0.25,>=0.24.0; extra == 'test'
